langchain_neo4j/__init__.py
langchain_neo4j/py.typed
langchain_neo4j/chains/__init__.py
langchain_neo4j/chains/graph_qa/__init__.py
langchain_neo4j/chains/graph_qa/cypher.py
langchain_neo4j/chains/graph_qa/cypher_utils.py
langchain_neo4j/chains/graph_qa/prompts.py
langchain_neo4j/chat_message_histories/__init__.py
langchain_neo4j/chat_message_histories/neo4j.py
langchain_neo4j/graphs/__init__.py
langchain_neo4j/graphs/graph_document.py
langchain_neo4j/graphs/graph_store.py
langchain_neo4j/graphs/neo4j_graph.py
langchain_neo4j/query_constructors/__init__.py
langchain_neo4j/query_constructors/neo4j.py
langchain_neo4j/vectorstores/__init__.py
langchain_neo4j/vectorstores/neo4j_vector.py
langchain_neo4j/vectorstores/utils.py
langchain_neo4j-0.7.0.dist-info/METADATA
langchain_neo4j-0.7.0.dist-info/WHEEL
langchain_neo4j-0.7.0.dist-info/licenses/LICENSE
langchain_neo4j-0.7.0.dist-info/RECORD
