Metadata-Version: 2.4
Name: langchain-neo4j
Version: 0.7.0
Summary: An integration package connecting Neo4j and LangChain
Project-URL: Release Notes, https://github.com/langchain-ai/langchain-neo4j/releases
Project-URL: Repository, https://github.com/langchain-ai/langchain-neo4j
Project-URL: Source Code, https://github.com/langchain-ai/langchain-neo4j/tree/main/libs/neo4j
License: MIT
License-File: LICENSE
Requires-Python: <3.15,>=3.10
Requires-Dist: langchain-classic<2.0.0,>=1.0.0
Requires-Dist: langchain-core<2.0.0,>=1.0.0
Requires-Dist: neo4j-graphrag<2.0.0,>=1.12.0
Requires-Dist: neo4j<7.0.0,>=5.25.0
Provides-Extra: mmr
Requires-Dist: numpy<3.0.0,>=2.1.0; extra == 'mmr'
